explainability/image/image_attacks.py
explainability/image/image_explanations.py
explainability/image/core/__init__.py
explainability/image/core/image_manipulator.py
explainability/lib/__init__.py
explainability/lib/trace.py
explainability/structured/__init__.py
explainability/structured/core/__init__.py
explainability/structured/core/structured_challenger.py
explainability/structured/core/structured_explainer.py
explainability/structured/core/structured_manipulator.py
explainability/structured/samples/__init__.py
explainability/structured/samples/challengers/__init__.py
explainability/structured/samples/challengers/categorize_challenger.py
explainability/structured/samples/challengers/replace_challenger.py
explainability/structured/samples/explainers/__init__.py
explainability/structured/samples/explainers/interpretml/__init__.py
explainability/structured/samples/explainers/interpretml/ebm_explainer.py
explainability/structured/samples/explainers/interpretml/morris_explainer.py
explainability/structured/samples/explainers/interpretml/pdp_explainer.py
explainability/ui/manage.py
explainability/ui/mysite/__init__.py
explainability/ui/mysite/asgi.py
explainability/ui/mysite/settings.py
explainability/ui/mysite/urls.py
explainability/ui/mysite/wsgi.py
explainability/ui/polls/__init__.py
explainability/ui/polls/admin.py
explainability/ui/polls/apps.py
explainability/ui/polls/urls.py
explainability/ui/polls/views.py
explainability/ui/polls/migrations/0001_initial.py
explainability/ui/polls/migrations/__init__.py
explainability_challenges-0.0.1.dist-info/LICENSE
explainability_challenges-0.0.1.dist-info/METADATA
explainability_challenges-0.0.1.dist-info/WHEEL
explainability_challenges-0.0.1.dist-info/top_level.txt
explainability_challenges-0.0.1.dist-info/RECORD
