Metadata-Version: 2.1
Name: explainability-challenges
Version: 0.0.1
Summary: A package implementing dataset alterations to test explainability methods for machine learning.
Author-email: Anna Cai <annacai@cs.cmu.edu>, Jacob Rast <jrast@cmu.edu>, Abhishek Vijayakumar <abhishev@cs.cmu.edu>
Project-URL: Homepage, https://github.com/inkyubeytor/explainability-challenges
Project-URL: Bug Tracker, https://github.com/inkyubeytor/explainability-challenges/issues
Classifier: Programming Language :: Python :: 3
Classifier: License :: OSI Approved :: MIT License
Classifier: Operating System :: OS Independent
Requires-Python: >=3.10
License-File: LICENSE
